pyhorn-0.9.0.dist-info/WHEEL
pyhorn-0.9.0.dist-info/metadata.json
pyhorn-0.9.0.dist-info/RECORD
pyhorn-0.9.0.dist-info/top_level.txt
pyhorn-0.9.0.dist-info/DESCRIPTION.rst
pyhorn-0.9.0.dist-info/METADATA
pyhorn/client.py
pyhorn/utils.py
pyhorn/__init__.py
pyhorn/endpoints/search.py
pyhorn/endpoints/workflow.py
pyhorn/endpoints/cache.py
pyhorn/endpoints/services.py
pyhorn/endpoints/episode.py
pyhorn/endpoints/usertracking.py
pyhorn/endpoints/__init__.py
pyhorn/endpoints/base.py
pyhorn/endpoints/info.py
pyhorn/endpoints/capture.py
