Metadata-Version: 2.0
Name: pyhorn
Version: 0.9.0
Summary: Python wrapper for the Matterhorn RESTful APIs
Home-page: https://bitbucket.org/lbjay/pyhorn
Author: Jay Luker
Author-email: lbjay@reallywow.com
License: Apache 2.0
Platform: UNKNOWN
Classifier: Development Status :: 3 - Alpha
Classifier: Intended Audience :: Developers
Classifier: Natural Language :: English
Classifier: License :: OSI Approved :: Apache Software License
Classifier: Programming Language :: Python
Classifier: Programming Language :: Python :: 3.6
Classifier: Programming Language :: Python :: 2.7
Requires-Dist: requests
Requires-Dist: requests-cache
Requires-Dist: arrow
Requires-Dist: rwlock
Requires-Dist: six
